{
  "iPhone_common_lines": {
    "PP_VDD_MAIN": {
      "iPhone_6": "400-450 Ω",
      "iPhone_7": "350-400 Ω",
      "iPhone_X": "300-350 Ω",
      "iPhone_11": "280-320 Ω",
      "iPhone_12": "250-300 Ω"
    },
    "PP_BATT_VCC": {
      "all_models": "50-100 KΩ"
    },
    "PP3V0_NAND": {
      "all_models": "300-400 Ω"
    },
    "PP1V8": {
      "all_models": "150-200 Ω"
    },
    "PP_CPU": {
      "all_models": "10-30 Ω"
    },
    "PP_GPU": {
      "iPhone_7_up": "20-40 Ω"
    }
  },
  "MacBook_common_lines": {
    "PPBUS_G3H": {
      "13_inch": "6-8 KΩ",
      "15_16_inch": "7-9 KΩ"
    },
    "PP3V3_G3H": {
      "all_models": "180-220 Ω"
    },
    "PP5V_G3S": {
      "all_models": "2.8-3.5 KΩ"
    },
    "PPVCORE_CPU": {
      "Intel": "1-3 Ω",
      "M1": "2-4 Ω"
    }
  }
}